{"AED":{"name":"United Arab Emirates dirham","mid":3.6724},"ARS":{"name":"Argentine peso","mid":9.5375},"AUD":{"name":"Australian dollar","mid":1.411632},"AZN":{"name":"Azerbaijanian manat","mid":1.0493},"BAM":{"name":"convertible marka","mid":1.770846},"BGN":{"name":"Bulgarian lev","mid":1.7692},"BRL":{"name":"Brazilian real","mid":3.842},"BYR":{"name":"Belarussian ruble","mid":17438},"CAD":{"name":"Canadian dollar","mid":1.3188},"CHF":{"name":"Swiss franc ","mid":0.991},"CLP":{"name":"Chilean peso","mid":690.75},"CNY":{"name":"Chinese renminbi","mid":6.318},"CZK":{"name":"Czech koruna","mid":24.5},"DKK":{"name":"Danish krone","mid":6.7899},"DOP":{"name":"Dominican peso","mid":45.05},"EGP":{"name":"Egyptian pound","mid":8.03},"EUR":{"name":"Euro","mid":0.910498},"GBP":{"name":"Pound sterling","mid":0.647375},"HKD":{"name":"Hong Kong dollar","mid":7.7494},"HRK":{"name":"Croatian kuna","mid":6.8611},"HUF":{"name":"Hungarian forint","mid":280.05},"ILS":{"name":"Israeli sheqel","mid":3.8673},"INR":{"name":"Indian rupee","mid":65.4096},"ISK":{"name":"Icelandic krona","mid":128.12},"JPY":{"name":"Japanese yen","mid":120.26},"LTL":{"name":"Lithuanian litas","mid":2.8536},"MAD":{"name":"Moroccan dirham","mid":9.764426},"MXN":{"name":"Mexican peso","mid":16.55215},"MYR":{"name":"Malaysian ringgit","mid":4.2985},"NOK":{"name":"Norwegian krone ","mid":8.594},"NZD":{"name":"New Zealand dollar","mid":1.48721},"PHP":{"name":"Philippine peso","mid":46.751},"PLN":{"name":"Polish zloty","mid":3.8435},"RON":{"name":"Romanian leu","mid":4.0118},"RSD":{"name":"Serbian dinar","mid":108.75},"RUB":{"name":"Russian ruble","mid":63.6525},"SAR":{"name":"Saudi riyal","mid":3.7503},"SEK":{"name":"Swedish krona","mid":8.5401},"SGD":{"name":"Singapore dollar","mid":1.4023},"THB":{"name":"Thai baht","mid":35.3532},"TND":{"name":"Tunisian dinar","mid":1.9653},"TRY":{"name":"Turkish lira ","mid":2.9149},"TWD":{"name":"Taiwan dollar","mid":32.437},"UAH":{"name":"Ukrainian hryvnia","mid":23.196},"VND":{"name":"Vietnam dong","mid":22313},"ZAR":{"name":"South African rand","mid":13.7607}}